Metadata-Version: 2.1
Name: majorityvoteproba
Version: 0.1.0
Summary: merge probability predictions for majority votes
Home-page: http://github.com/kmedian/majorityvoteproba
Author: Ulf Hamster
Author-email: 554c46@gmail.com
License: MIT
Platform: UNKNOWN
Requires-Python: >=3.6
